pandoc_latex_tip/__init__.py
pandoc_latex_tip/_app.py
pandoc_latex_tip/_main.py
pandoc_latex_tip-3.2.1.0.data/data/share/pandoc_latex_tip/fontawesome/brands.css
pandoc_latex_tip-3.2.1.0.data/data/share/pandoc_latex_tip/fontawesome/fa-brands-400.ttf
pandoc_latex_tip-3.2.1.0.data/data/share/pandoc_latex_tip/fontawesome/fa-regular-400.ttf
pandoc_latex_tip-3.2.1.0.data/data/share/pandoc_latex_tip/fontawesome/fa-solid-900.ttf
pandoc_latex_tip-3.2.1.0.data/data/share/pandoc_latex_tip/fontawesome/fontawesome.css
pandoc_latex_tip-3.2.1.0.dist-info/METADATA
pandoc_latex_tip-3.2.1.0.dist-info/WHEEL
pandoc_latex_tip-3.2.1.0.dist-info/entry_points.txt
pandoc_latex_tip-3.2.1.0.dist-info/licenses/LICENSE
pandoc_latex_tip-3.2.1.0.dist-info/RECORD
