Metadata-Version: 2.4
Name: pandoc-latex-tip
Version: 3.2.1.0
Summary: A pandoc filter for adding icons on specific elements
Project-URL: Homepage, https://github.com/chdemko/pandoc-latex-tip
Project-URL: Documentation, https://pandoc-latex-tip.readthedocs.io/
Project-URL: Repository, https://github.com/chdemko/pandoc-latex-tip
Project-URL: Issues, https://github.com/chdemko/pandoc-latex-tip/issues
Project-URL: Coverage, https://coveralls.io/github/chdemko/pandoc-latex-tip
Author-email: Christophe Demko <chdemko@gmail.com>
Maintainer-email: Christophe Demko <chdemko@gmail.com>
License: BSD-3-Clause
License-File: LICENSE
Keywords: Font-Awesome,filters,icon,latex,pandoc,tip
Classifier: Development Status :: 5 - Production/Stable
Classifier: Environment :: Console
Classifier: Intended Audience :: Developers
Classifier: Intended Audience :: End Users/Desktop
Classifier: Natural Language :: English
Classifier: Operating System :: OS Independent
Classifier: Programming Language :: Python :: 3.10
Classifier: Programming Language :: Python :: 3.11
Classifier: Programming Language :: Python :: 3.12
Classifier: Programming Language :: Python :: 3.13
Classifier: Topic :: Software Development :: Build Tools
Classifier: Topic :: Software Development :: Documentation
Classifier: Topic :: Text Processing :: Filters
Requires-Python: <3.14,>=3.10
Requires-Dist: cleo~=2.1
Requires-Dist: fonttools~=4.56
Requires-Dist: panflute~=2.3
Requires-Dist: pillow~=11.1
Requires-Dist: platformdirs~=4.3
Requires-Dist: pyyaml~=6.0
Requires-Dist: tinycss2~=1.4
